arrayed_degradation/__init__.py
arrayed_degradation/analyze_experiment.py
arrayed_degradation/analyze_single_rna.py
arrayed_degradation/decay_curve.py
arrayed_degradation/exceptions.py
arrayed_degradation/fails.py
arrayed_degradation/input_data.py
arrayed_degradation/log.py
arrayed_degradation/peaks.py
arrayed_degradation/plots.py
arrayed_degradation/results.py
arrayed_degradation/tests/__init__.py
arrayed_degradation/tests/test_decay_curve.py
arrayed_degradation/tests/test_e2e.py
arrayed_degradation/tests/test_fails.py
arrayed_degradation/tests/test_input_data.py
arrayed_degradation/tests/test_peaks.py
arrayed_degradation/tests/utils.py
arrayed_degradation_assay-0.1.3.dist-info/METADATA
arrayed_degradation_assay-0.1.3.dist-info/WHEEL
arrayed_degradation_assay-0.1.3.dist-info/entry_points.txt
arrayed_degradation_assay-0.1.3.dist-info/licenses/LICENSE.txt
arrayed_degradation_assay-0.1.3.dist-info/RECORD
