Metadata-Version: 2.3
Name: arrayed-degradation-assay
Version: 0.1.3
Summary: Analyse the data for RNA stability assay
Author-email: Inceptive Developers <opensource@inceptive.team>
License: Apache-2.0
Requires-Python: >=3.10
Requires-Dist: kaleido==0.2.1
Requires-Dist: numpy==1.23.*
Requires-Dist: pandas>=2.0.3
Requires-Dist: pathy==0.10.*
Requires-Dist: pillow==9.5.*
Requires-Dist: plotly==5.14.*
Requires-Dist: scikit-learn==1.2.*
Requires-Dist: scipy==1.11.*
Requires-Dist: tqdm==4.65.*
